eunomia/__init__.py
eunomia/_core.py
eunomia/backend/__init__.py
eunomia/backend/_backend.py
eunomia/backend/_backend_dict.py
eunomia/backend/_backend_obj.py
eunomia/backend/_backend_yaml.py
eunomia/backend/_helper.py
eunomia/config/__init__.py
eunomia/config/_config.py
eunomia/config/_config_debug.py
eunomia/config/_default.py
eunomia/config/_loader.py
eunomia/config/keys.py
eunomia/config/validate.py
eunomia/config/nodes/__init__.py
eunomia/config/nodes/_nodes.py
eunomia/config/nodes/_util_interpret.py
eunomia/config/nodes/_util_lark.py
eunomia/config/nodes/grammar_substitute.lark
eunomia/registry/__init__.py
eunomia/registry/_objects.py
eunomia/util/__init__.py
eunomia/util/_targets.py
eunomia/util/_util_attrdict.py
eunomia/util/_util_dict.py
eunomia/util/_util_traverse.py
tests/__init__.py
tests/test_backend_obj.py
tests/test_backend_yaml.py
tests/test_backends.py
tests/test_config_debug.py
tests/test_config_defaults.py
tests/test_config_objects.py
tests/test_config_schema.py
tests/test_core.py
tests/test_dict_util.py
tests/test_docs_examples.py
tests/test_nodes.py
tests/test_nodes_interpreter.py
tests/test_nodes_lark.py
tests/test_registry.py
tests/test_util_attrdict.py
tests/test_util_targets.py
tests/util.py
eunomia-0.0.1.dev20.dist-info/LICENSE
eunomia-0.0.1.dev20.dist-info/METADATA
eunomia-0.0.1.dev20.dist-info/WHEEL
eunomia-0.0.1.dev20.dist-info/top_level.txt
eunomia-0.0.1.dev20.dist-info/RECORD
