Metadata-Version: 2.1
Name: eunomia
Version: 0.0.1.dev20
Summary: Simple configuration framework with custom backends, based on hydra config.
Home-page: https://github.com/nmichlo/eunomia
Author: Nathan Juraj Michlo
Author-email: NathanJMichlo@gmail.com
License: UNKNOWN
Platform: UNKNOWN
Classifier: License :: OSI Approved :: MIT License
Classifier: Operating System :: OS Independent
Classifier: Programming Language :: Python :: 3.6
Classifier: Programming Language :: Python :: 3.7
Classifier: Programming Language :: Python :: 3.8
Classifier: Programming Language :: Python :: 3.9
Classifier: Intended Audience :: Science/Research
Requires-Python: >=3.6
Requires-Dist: asteval (==0.9.22)
Requires-Dist: lark-parser (==0.11.1)
Requires-Dist: ruamel.yaml (==0.16.12)
